[
  {
    "Ghar": "Aneriye All Including Bhaginman",
    "Is Babhnaiye": "NO",
    "Pratham Purush": "Neelkanth Jha",
    "Waasi": "",
    "Gotra": "",
    "Mool": "",
    "Total Male People": 1260,
    "Total Male Alive": 800,
    "Total Male Deceased": 460
  },
  {
    "Ghar": "Aneriye",
    "Is Babhnaiye": "NO",
    "Pratham Purush": "Praduymna Roy",
    "Waasi": "Bhirha -> Hansi -> Deokuli",
    "Gotra": "Sandilya",
    "Mool": "Peerapur",
    "Total Male People": 1235,
    "Total Male Alive": 778,
    "Total Male Deceased": 457
  },
  {
    "Ghar": "Anerieye Bhaginman",
    "Is Babhnaiye": "",
    "Pratham Purush": "",
    "Waasi": "",
    "Gotra": "",
    "Mool": "",
    "Total Male People": 25,
    "Total Male Alive": 22,
    "Total Male Deceased": 3
  },
  {
    "Ghar": "Anerieye Bhaginman Fucho Jha Nawada",
    "Is Babhnaiye": "NO",
    "Pratham Purush": "Sobhakant Jha",
    "Waasi": "Nawada",
    "Gotra": "",
    "Mool": "",
    "Total Male People": 12,
    "Total Male Alive": 10,
    "Total Male Deceased": 2
  },
  {
    "Ghar": "Anerieye Bhaginman Ram Manoj Chaudhary Sahasram",
    "Is Babhnaiye": "NO",
    "Pratham Purush": "Ramanuj Choudhary",
    "Waasi": "Sahasram",
    "Gotra": "",
    "Mool": "",
    "Total Male People": 11,
    "Total Male Alive": 10,
    "Total Male Deceased": 1
  },
  {
    "Ghar": "Anerieye Bhaginman Chandra Sekhar Roy Bithauli",
    "Is Babhnaiye": "NO",
    "Pratham Purush": "",
    "Waasi": "Bithauli",
    "Gotra": "",
    "Mool": "",
    "Total Male People": 2,
    "Total Male Alive": 2,
    "Total Male Deceased": ""
  },
  {
    "Ghar": "",
    "Is Babhnaiye": "",
    "Pratham Purush": "",
    "Waasi": "",
    "Gotra": "",
    "Mool": "",
    "Total Male People": "",
    "Total Male Alive": "",
    "Total Male Deceased": ""
  },
  {
    "Ghar": "Babhnaiyai All",
    "Is Babhnaiye": "",
    "Pratham Purush": "",
    "Waasi": "",
    "Gotra": "",
    "Mool": "",
    "Total Male People": 608,
    "Total Male Alive": 462,
    "Total Male Deceased": 146
  },
  {
    "Ghar": "Bhaginman Hansi Wala Aneriye",
    "Is Babhnaiye": "NO",
    "Pratham Purush": "Sobhakant Roy",
    "Waasi": "Hansi",
    "Gotra": "Sandilya",
    "Mool": "Peerapur",
    "Total Male People": 13,
    "Total Male Alive": 11,
    "Total Male Deceased": 2
  },
  {
    "Ghar": "Kari Kummar",
    "Is Babhnaiye": "YES",
    "Pratham Purush": "",
    "Waasi": "",
    "Gotra": "",
    "Mool": "",
    "Total Male People": 57,
    "Total Male Alive": 44,
    "Total Male Deceased": 13
  },
  {
    "Ghar": "Kari Kummar All",
    "Is Babhnaiye": "YES",
    "Pratham Purush": "",
    "Waasi": "",
    "Gotra": "",
    "Mool": "",
    "Total Male People": 70,
    "Total Male Alive": 55,
    "Total Male Deceased": 15
  },
  {
    "Ghar": "Kummar Tetrahi",
    "Is Babhnaiye": "YES",
    "Pratham Purush": "",
    "Waasi": "",
    "Gotra": "",
    "Mool": "",
    "Total Male People": 199,
    "Total Male Alive": 151,
    "Total Male Deceased": 48
  },
  {
    "Ghar": "Thakur",
    "Is Babhnaiye": "YES",
    "Pratham Purush": "Gopi Thakur",
    "Waasi": "Bhith Bhagwanpur",
    "Gotra": "Sandilya",
    "Mool": "",
    "Total Male People": 92,
    "Total Male Alive": 74,
    "Total Male Deceased": 18
  },
  {
    "Ghar": "Vinod Jha",
    "Is Babhnaiye": "YES",
    "Pratham Purush": "",
    "Waasi": "",
    "Gotra": "",
    "Mool": "",
    "Total Male People": 56,
    "Total Male Alive": 36,
    "Total Male Deceased": 20
  },
  {
    "Ghar": "Lukhar Jha",
    "Is Babhnaiye": "YES",
    "Pratham Purush": "Bhatu Jha",
    "Waasi": "Kabilpur",
    "Gotra": "",
    "Mool": "",
    "Total Male People": 26,
    "Total Male Alive": 19,
    "Total Male Deceased": 7
  },
  {
    "Ghar": "Buchkun Jha",
    "Is Babhnaiye": "YES",
    "Pratham Purush": "Gharbharan Jha",
    "Waasi": "Kaligaon",
    "Gotra": "Bharadwaj",
    "Mool": "",
    "Total Male People": 11,
    "Total Male Alive": 10,
    "Total Male Deceased": 1
  },
  {
    "Ghar": "Pandiji Jha",
    "Is Babhnaiye": "YES",
    "Pratham Purush": "Ramdhari Jha",
    "Waasi": "",
    "Gotra": "",
    "Mool": "",
    "Total Male People": 54,
    "Total Male Alive": 46,
    "Total Male Deceased": 8
  },
  {
    "Ghar": "Mishra",
    "Is Babhnaiye": "YES",
    "Pratham Purush": "Dharmdutt Mishra",
    "Waasi": "Kahua",
    "Gotra": "",
    "Mool": "",
    "Total Male People": 75,
    "Total Male Alive": 57,
    "Total Male Deceased": 18
  },
  {
    "Ghar": "Chandrakant Jha",
    "Is Babhnaiye": "YES",
    "Pratham Purush": "",
    "Waasi": "",
    "Gotra": "",
    "Mool": "",
    "Total Male People": 16,
    "Total Male Alive": 8,
    "Total Male Deceased": 8
  },
  {
    "Ghar": "Daani Jha",
    "Is Babhnaiye": "YES",
    "Pratham Purush": "",
    "Waasi": "",
    "Gotra": "",
    "Mool": "",
    "Total Male People": 9,
    "Total Male Alive": 6,
    "Total Male Deceased": 3
  },
  {
    "Ghar": "",
    "Is Babhnaiye": "",
    "Pratham Purush": "",
    "Waasi": "",
    "Gotra": "",
    "Mool": "",
    "Total Male People": "",
    "Total Male Alive": "",
    "Total Male Deceased": ""
  },
  {
    "Ghar": "",
    "Is Babhnaiye": "",
    "Pratham Purush": "",
    "Waasi": "",
    "Gotra": "",
    "Mool": "",
    "Total Male People": "",
    "Total Male Alive": "",
    "Total Male Deceased": ""
  },
  {
    "Ghar": "All",
    "Is Babhnaiye": "",
    "Pratham Purush": "",
    "Waasi": "",
    "Gotra": "",
    "Mool": "",
    "Total Male People": 1868,
    "Total Male Alive": 1262,
    "Total Male Deceased": 606
  },
  {
    "Ghar": "",
    "Is Babhnaiye": "",
    "Pratham Purush": "",
    "Waasi": "",
    "Gotra": "",
    "Mool": "",
    "Total Male People": "",
    "Total Male Alive": "",
    "Total Male Deceased": ""
  },
  {
    "Ghar": "Anerieye All",
    "Is Babhnaiye": "",
    "Pratham Purush": "",
    "Waasi": "",
    "Gotra": "",
    "Mool": "",
    "Total Male People": 1269,
    "Total Male Alive": 808,
    "Total Male Deceased": 462
  },
  {
    "Ghar": "Pahil Aath Aana",
    "Is Babhnaiye": "",
    "Pratham Purush": "Tula Krishna Roy",
    "Waasi": "",
    "Gotra": "",
    "Mool": "",
    "Total Male People": 468,
    "Total Male Alive": 307,
    "Total Male Deceased": 160
  },
  {
    "Ghar": "Baake Roy Ghar",
    "Is Babhnaiye": "",
    "Pratham Purush": "Mani Roy",
    "Waasi": "",
    "Gotra": "",
    "Mool": "",
    "Total Male People": 311,
    "Total Male Alive": 191,
    "Total Male Deceased": 119
  },
  {
    "Ghar": "Baake Roy Ghar Purab",
    "Is Babhnaiye": "",
    "Pratham Purush": "&1",
    "Waasi": "",
    "Gotra": "",
    "Mool": "",
    "Total Male People": 149,
    "Total Male Alive": "",
    "Total Male Deceased": ""
  },
  {
    "Ghar": "Baake Roy Ghar Paschim",
    "Is Babhnaiye": "",
    "Pratham Purush": "2&3",
    "Waasi": "",
    "Gotra": "",
    "Mool": "",
    "Total Male People": 162,
    "Total Male Alive": "",
    "Total Male Deceased": ""
  },
  {
    "Ghar": "Ajab Narayan Roy Ghar",
    "Is Babhnaiye": "",
    "Pratham Purush": "Tulsi Roy",
    "Waasi": "",
    "Gotra": "",
    "Mool": "",
    "Total Male People": 157,
    "Total Male Alive": 116,
    "Total Male Deceased": 41
  },
  {
    "Ghar": "",
    "Is Babhnaiye": "",
    "Pratham Purush": "",
    "Waasi": "",
    "Gotra": "",
    "Mool": "",
    "Total Male People": "",
    "Total Male Alive": "",
    "Total Male Deceased": ""
  },
  {
    "Ghar": "Dosar Aath Aana",
    "Is Babhnaiye": "",
    "Pratham Purush": "Kala Krishna  Roy",
    "Waasi": "",
    "Gotra": "",
    "Mool": "",
    "Total Male People": 801,
    "Total Male Alive": 501,
    "Total Male Deceased": 302
  },
  {
    "Ghar": "Pachkhuti",
    "Is Babhnaiye": "",
    "Pratham Purush": "Karo Roy",
    "Waasi": "",
    "Gotra": "",
    "Mool": "",
    "Total Male People": 334,
    "Total Male Alive": 216,
    "Total Male Deceased": 118
  },
  {
    "Ghar": "Pachkhuti Bichla Tol",
    "Is Babhnaiye": "",
    "Pratham Purush": "Hari Dutt Roy",
    "Waasi": "",
    "Gotra": "",
    "Mool": "",
    "Total Male People": "",
    "Total Male Alive": "",
    "Total Male Deceased": ""
  },
  {
    "Ghar": "Pachkhuti Pachhwari Tol",
    "Is Babhnaiye": "",
    "Pratham Purush": "",
    "Waasi": "",
    "Gotra": "",
    "Mool": "",
    "Total Male People": "",
    "Total Male Alive": "",
    "Total Male Deceased": ""
  },
  {
    "Ghar": "Taikhuti",
    "Is Babhnaiye": "",
    "Pratham Purush": "Pran Singh Roy",
    "Waasi": "",
    "Gotra": "",
    "Mool": "",
    "Total Male People": 199,
    "Total Male Alive": 133,
    "Total Male Deceased": 70
  },
  {
    "Ghar": "Taikhuti 4 farik",
    "Is Babhnaiye": "",
    "Pratham Purush": "Gangaram Roy",
    "Waasi": "",
    "Gotra": "",
    "Mool": "",
    "Total Male People": 130,
    "Total Male Alive": 96,
    "Total Male Deceased": 34
  },
  {
    "Ghar": "Taikhuti 4 farik dih",
    "Is Babhnaiye": "",
    "Pratham Purush": "Dullar Roy",
    "Waasi": "",
    "Gotra": "",
    "Mool": "",
    "Total Male People": 69,
    "Total Male Alive": 37,
    "Total Male Deceased": 36
  },
  {
    "Ghar": "Choubhaiya",
    "Is Babhnaiye": "",
    "Pratham Purush": "Raghunath Roy",
    "Waasi": "",
    "Gotra": "",
    "Mool": "",
    "Total Male People": 268,
    "Total Male Alive": 152,
    "Total Male Deceased": 114
  },
  {
    "Ghar": "Choubhaiya Purab",
    "Is Babhnaiye": "",
    "Pratham Purush": "3&4",
    "Waasi": "",
    "Gotra": "",
    "Mool": "",
    "Total Male People": 174,
    "Total Male Alive": "",
    "Total Male Deceased": ""
  },
  {
    "Ghar": "Choubhiya Paschim",
    "Is Babhnaiye": "",
    "Pratham Purush": "1&2",
    "Waasi": "",
    "Gotra": "",
    "Mool": "",
    "Total Male People": 94,
    "Total Male Alive": "",
    "Total Male Deceased": ""
  }
]